odtbrain/__init__.py
odtbrain/_alg2d_bpp.py
odtbrain/_alg2d_fmp.py
odtbrain/_alg2d_int.py
odtbrain/_alg3d_bpp.py
odtbrain/_alg3d_bppt.py
odtbrain/_prepare_sino.py
odtbrain/_translate_ri.py
odtbrain/_version.py
odtbrain/apple.py
odtbrain/util.py
odtbrain/warn.py
odtbrain-0.4.12.dist-info/licenses/LICENSE
odtbrain-0.4.12.dist-info/METADATA
odtbrain-0.4.12.dist-info/WHEEL
odtbrain-0.4.12.dist-info/top_level.txt
odtbrain-0.4.12.dist-info/RECORD
