Metadata-Version: 2.4
Name: ODTbrain
Version: 0.4.12
Summary: Algorithms for diffraction tomography
Author: Paul Müller
Maintainer-email: Paul Müller <dev@craban.de>
License: Copyright (c) 2015, Paul Müller
Project-URL: source, https://github.com/RI-imaging/ODTbrain
Project-URL: tracker, https://github.com/RI-imaging/ODTbrain/Issues
Keywords: odt,opt,diffraction,born,rytov,radon,backprojection,backpropagation,inverse problem,Fourier diffraction theorem,Fourier slice theorem
Classifier: Operating System :: OS Independent
Classifier: Programming Language :: Python :: 3
Classifier: Topic :: Scientific/Engineering :: Visualization
Classifier: Intended Audience :: Science/Research
Requires-Python: <4,>=3.5
License-File: LICENSE
Requires-Dist: numexpr
Requires-Dist: numpy>=1.7.0
Requires-Dist: pyfftw<1,>=0.9.2
Requires-Dist: scikit-image<1,>=0.21.0
Requires-Dist: scipy<2,>=1.4.0
Dynamic: license-file
